<?xml version="1.0" encoding="UTF-8"?>
<addon id="plugin.video.indavideo"
version="0.0.1"
name="Indavideó"
provider-name="holiday">
<requires>
  <import addon="xbmc.python" version="2.24.0"/>
</requires>
<extension point="xbmc.python.pluginsource" library="main.py">
  <provides>video</provides>
</extension>
<extension point="xbmc.addon.metadata">
  <summary lang="en">Indavideó</summary>
  <description lang="en">Indavideó</description>
  <disclaimer lang="en">Provided by http://www.indavideo.hu.</disclaimer>
</extension>
</addon>
